mm_http/__init__.py
mm_http/py.typed
mm_http/request.py
mm_http/request_sync.py
mm_http/response.py
mm_http-0.3.0.dist-info/METADATA
mm_http-0.3.0.dist-info/WHEEL
mm_http-0.3.0.dist-info/RECORD
