Metadata-Version: 2.4
Name: mm-http
Version: 0.3.0
Requires-Python: >=3.14
Requires-Dist: aiohttp-socks~=0.11.0
Requires-Dist: aiohttp~=3.13.3
Requires-Dist: mm-result~=0.2.0
Requires-Dist: pydantic~=2.12.5
Requires-Dist: pydash~=8.0.6
Requires-Dist: requests[socks]~=2.32.5
